controlchart/__init__.py
python_controlchart-0.2.0.dist-info/LICENSE
python_controlchart-0.2.0.dist-info/METADATA
python_controlchart-0.2.0.dist-info/WHEEL
python_controlchart-0.2.0.dist-info/top_level.txt
python_controlchart-0.2.0.dist-info/RECORD
